fixedincome/__init__.py
fixedincome/bonds.py
fixedincome/utils.py
fixedincome/yield_curve.py
fixedincome_analytics-0.1.3.dist-info/LICENSE
fixedincome_analytics-0.1.3.dist-info/METADATA
fixedincome_analytics-0.1.3.dist-info/WHEEL
fixedincome_analytics-0.1.3.dist-info/top_level.txt
fixedincome_analytics-0.1.3.dist-info/RECORD
