Metadata-Version: 2.1
Name: fixedincome-analytics
Version: 0.1.3
Summary: Fixed Income Securities and Derivatives analytics package
Home-page: https://github.com/shreysrins/FixedIncome
Author: Shreyas V. Srinivasan
Author-email: shreyass@alum.mit.edu
License: UNKNOWN
Project-URL: Bug Tracker, https://github.com/shreysrins/FixedIncome/issues
Platform: UNKNOWN
Classifier: Programming Language :: Python :: 3.7
Classifier: License :: OSI Approved :: MIT License
Classifier: Operating System :: OS Independent
Requires-Python: >=3.7
License-File: LICENSE
Requires-Dist: numpy
Requires-Dist: scipy
Requires-Dist: python-dateutil
